[{"id":1,"nombre":"Administrador","descripcion":"Usuario con acceso completo al sistema","activo":true,"creado_en":"2025-11-14 21:39:42.022695"},{"id":2,"nombre":"Director","descripcion":"Director de departamento con permisos de aprobación","activo":false,"creado_en":"2025-11-14 21:39:42.022695"},{"id":3,"nombre":"Usuario","descripcion":"Usuario regular del departamento","activo":false,"creado_en":"2025-11-14 21:39:42.022695"},{"id":4,"nombre":"Almacenista","descripcion":"Usuario encargado del almacén","activo":false,"creado_en":"2025-11-14 21:39:42.022695"},{"id":5,"nombre":"Dirección Administrativa","descripcion":"Rol para dirección administrativa del sistema","activo":true,"creado_en":"2025-11-15 02:52:32.177359"},{"id":6,"nombre":"Encargado de Suministro","descripcion":"Rol para encargados de suministro","activo":true,"creado_en":"2025-11-15 02:52:32.177359"},{"id":7,"nombre":"Suministro","descripcion":"Rol para personal de suministro","activo":true,"creado_en":"2025-11-15 02:52:32.177359"},{"id":8,"nombre":"Departamento","descripcion":"Rol para usuarios de departamento","activo":true,"creado_en":"2025-11-15 02:52:32.177359"}]

